<?xml version="1.0" encoding="UTF-8" standalone="yes"?>
<configurations>
    <configuration>
        <categories>
            <categoriesName>lab3.logger.main.Main</categoriesName>
        </categories>
        <levelApenderList>
            <appender>
                <nameAppender>lab3.logger.append.ConsolAppender</nameAppender>
                <layout>
                    <layouts>%p %c %m %d</layouts>
                </layout>
            </appender>
            <level>
                <levelValue>2</levelValue>
                <levelStr>WARN</levelStr>
            </level>
        </levelApenderList>
    </configuration>
    <configuration>
        <categories>
            <categoriesName>lab3.logger</categoriesName>
        </categories>
        <levelApenderList>
            <appender>
                <nameAppender>lab3.logger.append.ConsolAppender</nameAppender>
                <layout>
                    <layouts>%p %d %m %c</layouts>
                </layout>
            </appender>
            <level>
                <levelValue>4</levelValue>
                <levelStr>DEBUG</levelStr>
            </level>
        </levelApenderList>
        <levelApenderList>
            <appender>
                <nameAppender>lab3.logger.append.ConsolAppender</nameAppender>
                <layout>
                    <layouts>%p %d %m %c</layouts>
                </layout>
            </appender>
            <level>
                <levelValue>5</levelValue>
                <levelStr>TRACE</levelStr>
            </level>
        </levelApenderList>
    </configuration>
</configurations>
